{
  "Settings_T_NumberMax": {
    "value": "Valore massimo: ${Num}",
    "original": {
      "value": "Maximum value: ${Num}"
    },
    "translatedBy": "ai",
    "isTranslated": true
  },
  "Settings_T_NumberMin": {
    "value": "Valore minimo: ${Num}",
    "original": {
      "value": "Minimum value: ${Num}"
    },
    "translatedBy": "ai",
    "isTranslated": true
  },
  "Settings_N_NAME-Search": {
    "value": "Ricerca su Internet",
    "original": {
      "value": "Internet Search",
      "version": 1
    },
    "translatedBy": "ai",
    "isTranslated": true,
    "version": 1
  },
  "Error_T_Problem": {
    "value": "Interruzione importante.",
    "original": {
      "value": "Major outage.",
      "version": 1
    },
    "translatedBy": "ai",
    "isTranslated": true,
    "version": 1
  },
  "Settings_N_NAME-Upd": {
    "value": "Controllo degli aggiornamenti",
    "original": {
      "value": "Checking for Updates",
      "version": 1
    },
    "translatedBy": "ai",
    "isTranslated": true,
    "version": 1
  },
  "Share_T_ErrorFile": {
    "value": "Purtroppo, Nuvole AI non può lavorare con questo file",
    "original": {
      "value": "Unfortunately, Nuvole AI cannot work with this file",
      "version": 1
    },
    "translatedBy": "ai",
    "isTranslated": true,
    "version": 1
  },
  "History_T_2Chats": {
    "value": "2 chat",
    "original": {
      "value": "2 chats",
      "version": 1
    },
    "translatedBy": "ai",
    "isTranslated": true,
    "version": 1
  },
  "Feedback_ORG_Email": {
    "value": "Puoi ottenere feedback dagli sviluppatori",
    "original": {
      "value": "You can get developer feedback"
    },
    "translatedBy": "ai",
    "isTranslated": true
  },
  "Text_T_Seconds": {
    "value": "Pensato per ${Num} secondi",
    "original": {
      "value": "Thought for ${Num} seconds",
      "version": 1
    },
    "translatedBy": "ai",
    "isTranslated": true,
    "version": 1
  },
  "Feedback_H_Type": {
    "value": "Come vuoi inviare il feedback?",
    "original": {
      "value": "How you want to send feedback?",
      "version": 1
    },
    "translatedBy": "ai",
    "isTranslated": true,
    "version": 1
  },
  "History_N_DeletionDelete": {
    "value": "Elimina tutte le chat",
    "original": {
      "value": "Delete All Chats",
      "version": 1
    },
    "translatedBy": "ai",
    "isTranslated": true,
    "version": 1
  },
  "Settings_H_NAME-Theme": {
    "value": "Seleziona l'aspetto da applicare alla visualizzazione delle risposte",
    "original": {
      "value": "Select the appearance to be applied to the display of responses",
      "version": 1
    },
    "translatedBy": "ai",
    "isTranslated": true,
    "version": 1
  },
  "Feedback_N_YesHistory": {
    "value": "Sì, trasmetti la cronologia di questa chat",
    "original": {
      "value": "Yes, Transmit the History of This Chat",
      "version": 1
    },
    "translatedBy": "ai",
    "isTranslated": true,
    "version": 1
  },
  "Feedback_H_End": {
    "value": "Messaggio inviato!",
    "original": {
      "value": "Message sent!",
      "version": 1
    },
    "translatedBy": "ai",
    "isTranslated": true,
    "version": 1
  },
  "Settings_T_ID-Voice-False": {
    "value": "Con testo",
    "original": {
      "value": "With Text",
      "version": 1
    },
    "translatedBy": "ai",
    "isTranslated": true,
    "version": 1
  },
  "Feedback_H_Config": {
    "value": "Vorresti trasmettere un file di configurazione delle impostazioni di Nuvole AI con lo sviluppatore?",
    "original": {
      "value": "Would you like to transmit a Nuvole AI settings configuration file with developer?"
    },
    "translatedBy": "ai",
    "isTranslated": true
  },
  "History_H_Selection": {
    "value": "Scegli quali chat vuoi eliminare",
    "original": {
      "value": "Choose which chats you want to delete",
      "version": 1
    },
    "translatedBy": "ai",
    "isTranslated": true,
    "version": 1
  },
  "Settings_T_ID-Theme-Auto": {
    "value": "Sistema",
    "original": {
      "value": "System",
      "version": 1
    },
    "translatedBy": "ai",
    "isTranslated": true,
    "version": 1
  },
  "Chat_N_Delete": {
    "value": "Elimina chat",
    "original": {
      "value": "Delete Chat",
      "version": 1
    },
    "translatedBy": "ai",
    "isTranslated": true,
    "version": 1
  },
  "Main_ORG_2Messages": {
    "value": "2 messaggi",
    "original": {
      "value": "2 messages",
      "version": 1
    },
    "translatedBy": "ai",
    "isTranslated": true,
    "version": 1
  },
  "Settings_T_ID-Save-False": {
    "value": "Solo su richiesta",
    "original": {
      "value": "Only on Request",
      "version": 1
    },
    "translatedBy": "ai",
    "isTranslated": true,
    "version": 1
  },
  "Update_T_5Updates": {
    "value": "5 aggiornamenti",
    "original": {
      "value": "5 updates",
      "version": 1
    },
    "translatedBy": "ai",
    "isTranslated": true,
    "version": 1
  },
  "Update_H_VersionCount": {
    "value": "Sono state rilasciate ${Count versioni} dalla versione ${Num}",
    "original": {
      "value": "${Count versions} have been released since version ${Num}",
      "version": 1
    },
    "translatedBy": "ai",
    "isTranslated": true,
    "version": 1
  },
  "Settings_T_ID-Upd-True": {
    "value": "Attivato",
    "original": {
      "value": "Turned On",
      "version": 1
    },
    "translatedBy": "ai",
    "isTranslated": true,
    "version": 1
  },
  "Settings_N_NAME-Main": {
    "value": "Menu principale",
    "original": {
      "value": "Main Menu",
      "version": 1
    },
    "translatedBy": "ai",
    "isTranslated": true,
    "version": 1
  },
  "Generation_H_H": {
    "value": "Avviso di gestione del dispositivo!",
    "original": {
      "value": "Device management alert!",
      "version": 1
    },
    "translatedBy": "ai",
    "isTranslated": true,
    "version": 1
  },
  "History_ORG_DeletionDelete": {
    "value": "Elimina permanentemente tutta la cronologia delle chat",
    "original": {
      "value": "Permanently delete all chat history"
    },
    "translatedBy": "ai",
    "isTranslated": true
  },
  "Settings_T_ID-Share-2": {
    "value": "Domanda",
    "original": {
      "value": "Question",
      "version": 1
    },
    "translatedBy": "ai",
    "isTranslated": true,
    "version": 1
  },
  "Update_N_Details": {
    "value": "Visualizza il registro completo delle modifiche",
    "original": {
      "value": "View Full Changelog"
    },
    "translatedBy": "ai",
    "isTranslated": true
  },
  "Install_N_YesMenu": {
    "value": "Apri il Menu Principale",
    "original": {
      "value": "Open the Main Menu"
    },
    "translatedBy": "ai",
    "isTranslated": true
  },
  "Main_N_Feedback": {
    "value": "Scrivi un feedback",
    "original": {
      "value": "Write a Feedback",
      "version": 1
    },
    "translatedBy": "ai",
    "isTranslated": true,
    "version": 1
  },
  "Main_H_Main": {
    "value": "Menu principale",
    "original": {
      "value": "Main Menu",
      "version": 1
    },
    "translatedBy": "ai",
    "isTranslated": true,
    "version": 1
  },
  "Share_H_Slides": {
    "value": "Seleziona le diapositive che vuoi utilizzare",
    "original": {
      "value": "Select the slides you want to use",
      "version": 1
    },
    "translatedBy": "ai",
    "isTranslated": true,
    "version": 1
  },
  "Error_T_Type-Error-4": {
    "value": "Si è verificato un errore durante la generazione dell'immagine!",
    "original": {
      "value": "An error occurred during image generation!"
    },
    "translatedBy": "ai",
    "isTranslated": true
  },
  "Update_H_2Versions": {
    "value": "2 versioni",
    "original": {
      "value": "2 versions",
      "version": 1
    },
    "translatedBy": "ai",
    "isTranslated": true,
    "version": 1
  },
  "Update_T_More": {
    "value": "Altro",
    "original": {
      "value": "More",
      "version": 1
    },
    "translatedBy": "ai",
    "isTranslated": true,
    "version": 1
  },
  "Text_T_HideNote": {
    "value": "Nascondi nota completa",
    "original": {
      "value": "Hide Full Note",
      "version": 1
    },
    "translatedBy": "ai",
    "isTranslated": true,
    "version": 1
  },
  "Text_T_Info": {
    "value": "Informazioni trovate",
    "original": {
      "value": "Found information"
    },
    "translatedBy": "ai",
    "isTranslated": true
  },
  "Error_T_Normal": {
    "value": "Tutti i sistemi funzionano correttamente.",
    "original": {
      "value": "All systems are working properly.",
      "version": 1
    },
    "translatedBy": "ai",
    "isTranslated": true,
    "version": 1
  },
  "Main_N_NewChat": {
    "value": "Crea una nuova chat",
    "original": {
      "value": "Create a New Chat",
      "version": 1
    },
    "translatedBy": "ai",
    "isTranslated": true,
    "version": 1
  },
  "Settings_N_Loading-False": {
    "value": "Crea nuova chat",
    "original": {
      "value": "Create New Chat",
      "version": 1
    },
    "translatedBy": "ai",
    "isTranslated": true,
    "version": 1
  },
  "Share_T_ErrorVideo": {
    "value": "Purtroppo, Nuvole AI non può lavorare con questo video",
    "original": {
      "value": "Unfortunately, Nuvole AI cannot work with this video",
      "version": 1
    },
    "translatedBy": "ai",
    "isTranslated": true,
    "version": 1
  },
  "Install_N_Learn": {
    "value": "Informazioni su Nuvole AI",
    "original": {
      "value": "About Nuvole AI"
    },
    "translatedBy": "ai",
    "isTranslated": true
  },
  "Chat_ORG_DeletionDelete": {
    "value": "Elimina permanentemente questa chat",
    "original": {
      "value": "Permanently delete this chat"
    },
    "translatedBy": "ai",
    "isTranslated": true
  },
  "Install_N_NoUpdates": {
    "value": "Non ricevere aggiornamenti",
    "original": {
      "value": "Do Not Receive Updates",
      "version": 1
    },
    "translatedBy": "ai",
    "isTranslated": true,
    "version": 1
  },
  "Settings_H_NAME-Search": {
    "value": "Vuoi che Nuvole AI cerchi informazioni su Internet, se necessario?",
    "original": {
      "value": "Do you want Nuvole AI to search for information on the Internet, if necessary?",
      "version": 1
    },
    "translatedBy": "ai",
    "isTranslated": true,
    "version": 1
  },
  "Text_T_Save": {
    "value": "La chat verrà salvata",
    "original": {
      "value": "Chat will be saved",
      "version": 1
    },
    "translatedBy": "ai",
    "isTranslated": true,
    "version": 1
  },
  "Update_T_5Changes": {
    "value": "5 modifiche",
    "original": {
      "value": "5 changes",
      "version": 1
    },
    "translatedBy": "ai",
    "isTranslated": true,
    "version": 1
  },
  "Settings_ORG_Close": {
    "value": "Continua la conversazione con Nuvole AI",
    "original": {
      "value": "Continue the conversation with Nuvole AI",
      "version": 1
    },
    "translatedBy": "ai",
    "isTranslated": true,
    "version": 1
  },
  "Share_H_SiteType": {
    "value": "Cosa vuoi fare con questo sito?",
    "original": {
      "value": "What do you want to do with this site?",
      "version": 1
    },
    "translatedBy": "ai",
    "isTranslated": true,
    "version": 1
  },
  "Settings_N_NAME-Theme": {
    "value": "Aspetto",
    "original": {
      "value": "Appearance",
      "version": 1
    },
    "translatedBy": "ai",
    "isTranslated": true,
    "version": 1
  },
  "Update_T_1Updates": {
    "value": "1 aggiornamento",
    "original": {
      "value": "1 update",
      "version": 1
    },
    "translatedBy": "ai",
    "isTranslated": true,
    "version": 1
  },
  "Settings_T_ID-Save-True": {
    "value": "Sempre",
    "original": {
      "value": "Always",
      "version": 1
    },
    "translatedBy": "ai",
    "isTranslated": true,
    "version": 1
  },
  "Chat_N_Load": {
    "value": "Carica e continua chat",
    "original": {
      "value": "Load and Continue Chat",
      "version": 1
    },
    "translatedBy": "ai",
    "isTranslated": true,
    "version": 1
  },
  "Text_T_HideThink": {
    "value": "Nascondi pensieri completi",
    "original": {
      "value": "Hide Full Throghts",
      "version": 1
    },
    "translatedBy": "ai",
    "isTranslated": true,
    "version": 1
  },
  "Error_ORG_Report": {
    "value": "Segnala un bug",
    "original": {
      "value": "Report a bug",
      "version": 1
    },
    "translatedBy": "ai",
    "isTranslated": true,
    "version": 1
  },
  "Error_T_ModelNotAvaiable": {
    "value": "Non disponibile al momento",
    "original": {
      "value": "Not available at the moment",
      "version": 1
    },
    "translatedBy": "ai",
    "isTranslated": true,
    "version": 1
  },
  "Settings_N_ImagePlus-False": {
    "value": "Non Migliorare Prompt",
    "original": {
      "value": "Do Not Improve Prompt"
    },
    "translatedBy": "ai",
    "isTranslated": true
  },
  "Settings_T_C-Next": {
    "value": "Cosa vuoi fare dopo?",
    "original": {
      "value": "What do you want to do next?",
      "version": 1
    },
    "translatedBy": "ai",
    "isTranslated": true,
    "version": 1
  },
  "Feedback_H_ReportInput": {
    "value": "Descrivi in dettaglio il problema che hai riscontrato",
    "original": {
      "value": "Describe in detail the problem you have encountered",
      "version": 1
    },
    "translatedBy": "ai",
    "isTranslated": true,
    "version": 1
  },
  "Settings_T_C-Share": {
    "value": "Foglio di condivisione",
    "original": {
      "value": "Share Sheet",
      "version": 1
    },
    "translatedBy": "ai",
    "isTranslated": true,
    "version": 1
  },
  "Main_ORG_History": {
    "value": "Sfoglia, visualizza e continua le tue chat",
    "original": {
      "value": "Browse, view and continue your chats"
    },
    "translatedBy": "ai",
    "isTranslated": true
  },
  "History_ORG_BackHistory": {
    "value": "Torna alla cronologia",
    "original": {
      "value": "Return to History",
      "version": 1
    },
    "translatedBy": "ai",
    "isTranslated": true,
    "version": 1
  },
  "Chat_ORG_DeletionStop": {
    "value": "Salva chat e torna indietro",
    "original": {
      "value": "Save chat and go back",
      "version": 1
    },
    "translatedBy": "ai",
    "isTranslated": true,
    "version": 1
  },
  "Install_N_YesUpdates": {
    "value": "Ricevi aggiornamenti",
    "original": {
      "value": "Receive Updates",
      "version": 1
    },
    "translatedBy": "ai",
    "isTranslated": true,
    "version": 1
  },
  "Share_H_FileType": {
    "value": "Cosa vuoi fare con questo file?",
    "original": {
      "value": "What do you want to do with this file?",
      "version": 1
    },
    "translatedBy": "ai",
    "isTranslated": true,
    "version": 1
  },
  "Update_T_1Changes": {
    "value": "1 modifica",
    "original": {
      "value": "1 change",
      "version": 1
    },
    "translatedBy": "ai",
    "isTranslated": true,
    "version": 1
  },
  "Share_T_ErrorSite": {
    "value": "Purtroppo, Nuvole AI non può lavorare con questo sito",
    "original": {
      "value": "Unfortunately, Nuvole AI cannot work with this site",
      "version": 1
    },
    "translatedBy": "ai",
    "isTranslated": true,
    "version": 1
  },
  "History_N_Search": {
    "value": "Cerca",
    "original": {
      "value": "Search",
      "version": 1
    },
    "translatedBy": "ai",
    "isTranslated": true,
    "version": 1
  },
  "Main_N_LastLoad": {
    "value": "Riprendi l'ultima chat",
    "original": {
      "value": "Resume Last Chat"
    },
    "translatedBy": "ai",
    "isTranslated": true
  },
  "Main_ORG_Ago": {
    "value": "${Secondi} fa",
    "original": {
      "value": "${Seconds} ago",
      "version": 1
    },
    "translatedBy": "ai",
    "isTranslated": true,
    "version": 1
  },
  "Share_T_SiteSize": {
    "value": "Fai un riassunto di ${Size} del sito",
    "original": {
      "value": "Make a ${Size} summarization of the site",
      "version": 1
    },
    "translatedBy": "ai",
    "isTranslated": true,
    "version": 1
  },
  "Error_ORG_RestartNew": {
    "value": "Verrà creata una nuova chat",
    "original": {
      "value": "New chat will be created",
      "version": 1
    },
    "translatedBy": "ai",
    "isTranslated": true,
    "version": 1
  },
  "Chat_H_Changing": {
    "value": "Quale icona vuoi dare a questa chat (puoi usare solo un emoji)?",
    "original": {
      "value": "What icon do you want to give this chat (you can use only one emoji)?",
      "version": 1
    },
    "translatedBy": "ai",
    "isTranslated": true,
    "version": 1
  },
  "Main_ORG_Feedback": {
    "value": "Qualsiasi problema, domanda o idea?",
    "original": {
      "value": "Any problems, questions or ideas?"
    },
    "translatedBy": "ai",
    "isTranslated": true
  },
  "Share_T_VideoSize": {
    "value": "Fai un riassunto di ${Size} del video",
    "original": {
      "value": "Make a ${Size} summarization of the video",
      "version": 1
    },
    "translatedBy": "ai",
    "isTranslated": true,
    "version": 1
  },
  "Share_H_BigPre": {
    "value": "Usare l'intera presentazione? O alcune diapositive?",
    "original": {
      "value": "Use the whole presentation? Or certain slides?",
      "version": 1
    },
    "translatedBy": "ai",
    "isTranslated": true,
    "version": 1
  },
  "Error_N_Restart": {
    "value": "Riavvia Nuvole AI",
    "original": {
      "value": "Restart Nuvole AI",
      "version": 1
    },
    "translatedBy": "ai",
    "isTranslated": true,
    "version": 1
  },
  "Update_H_Update": {
    "value": "È disponibile un nuovo aggiornamento per Nuvole AI!",
    "original": {
      "value": "A new update for Nuvole AI is available!",
      "version": 1
    },
    "translatedBy": "ai",
    "isTranslated": true,
    "version": 1
  },
  "Settings_N_NAME-Model": {
    "value": "Modello AI",
    "original": {
      "value": "AI Model",
      "version": 1
    },
    "translatedBy": "ai",
    "isTranslated": true,
    "version": 1
  },
  "Settings_N_Saving-True": {
    "value": "Salva sempre nuove chat",
    "original": {
      "value": "Always Save New Chats",
      "version": 1
    },
    "translatedBy": "ai",
    "isTranslated": true,
    "version": 1
  },
  "Share_T_FileSize": {
    "value": "Fai un riassunto di ${Size} del file",
    "original": {
      "value": "Make a ${Size} summarization of the file",
      "version": 1
    },
    "translatedBy": "ai",
    "isTranslated": true,
    "version": 1
  },
  "Settings_T_ID-Summary-1": {
    "value": "Piccolo",
    "original": {
      "value": "Small",
      "version": 1
    },
    "translatedBy": "ai",
    "isTranslated": true,
    "version": 1
  },
  "Settings_T_ID-Theme-1": {
    "value": "Scuro",
    "original": {
      "value": "Dark",
      "version": 1
    },
    "translatedBy": "ai",
    "isTranslated": true,
    "version": 1
  },
  "Settings_T_ID-Summary-Ask": {
    "value": "Chiedi ogni volta",
    "original": {
      "value": "Ask Every Time",
      "version": 1
    },
    "translatedBy": "ai",
    "isTranslated": true,
    "version": 1
  },
  "Error_N_Replace": {
    "value": "Riprova con il modello temporaneo",
    "original": {
      "value": "Retry With Temp Model"
    },
    "translatedBy": "ai",
    "isTranslated": true
  },
  "H_ModelUpdate": {
    "value": "Sembra che il modello ${Name} che hai selezionato in precedenza non sia più disponibile. Quale modello AI vuoi utilizzare?",
    "original": {
      "value": "It looks like the model ${Name} you selected earlier is no longer available. Which AI model would you like to use?",
      "version": 1
    },
    "translatedBy": "ai",
    "isTranslated": true,
    "version": 1
  },
  "Install_N_NoMenu": {
    "value": "Non aprire il menu principale",
    "original": {
      "value": "Don’t Open the Main Menu"
    },
    "translatedBy": "ai",
    "isTranslated": true
  },
  "Chat_T_ChangingError": {
    "value": "Solo emoji possono essere usati come icona",
    "original": {
      "value": "Only emojis can be used as an icon",
      "version": 1
    },
    "translatedBy": "ai",
    "isTranslated": true,
    "version": 1
  },
  "Feedback_N_NoHistory": {
    "value": "No, non trasmettere la cronologia",
    "original": {
      "value": "No, Not Transmit the History",
      "version": 1
    },
    "translatedBy": "ai",
    "isTranslated": true,
    "version": 1
  },
  "History_N_Select": {
    "value": "Seleziona ed elimina chat",
    "original": {
      "value": "Select and Delete Chats",
      "version": 1
    },
    "translatedBy": "ai",
    "isTranslated": true,
    "version": 1
  },
  "History_N_Delete": {
    "value": "Elimina tutte le chat",
    "original": {
      "value": "Delete All Chats",
      "version": 1
    },
    "translatedBy": "ai",
    "isTranslated": true,
    "version": 1
  },
  "History_T_1Chats": {
    "value": "1 chat",
    "original": {
      "value": "1 chat",
      "version": 1
    },
    "translatedBy": "ai",
    "isTranslated": true,
    "version": 1
  },
  "Error_T_Type-Error-3": {
    "value": "Si è verificato un errore durante la generazione del testo!",
    "original": {
      "value": "An error occurred during text generation!"
    },
    "translatedBy": "ai",
    "isTranslated": true
  },
  "Settings_N_NAME-ImagePlus": {
    "value": "Migliora il Prompt",
    "original": {
      "value": "Enchance the Prompt"
    },
    "translatedBy": "ai",
    "isTranslated": true
  },
  "Settings_H_NAME-Loading": {
    "value": "Vuoi creare una nuova chat o caricare e continuare l'ultima quando esegui Nuvole AI?",
    "original": {
      "value": "Do you want to create a new chat or load and continue the last one when running Nuvole AI?",
      "version": 1
    },
    "translatedBy": "ai",
    "isTranslated": true,
    "version": 1
  },
  "History_ORG_DeletionStop": {
    "value": "Salva chat e torna indietro",
    "original": {
      "value": "Save chats and go back",
      "version": 1
    },
    "translatedBy": "ai",
    "isTranslated": true,
    "version": 1
  },
  "Chat_N_Icon": {
    "value": "Cambia icona chat",
    "original": {
      "value": "Change Chat Icon",
      "version": 1
    },
    "translatedBy": "ai",
    "isTranslated": true,
    "version": 1
  },
  "Text_T_Show": {
    "value": "Mostra messaggio completo",
    "original": {
      "value": "Show Full Message",
      "version": 1
    },
    "translatedBy": "ai",
    "isTranslated": true,
    "version": 1
  },
  "Update_N_Install": {
    "value": "Installa una nuova versione ${Num}",
    "original": {
      "value": "Install a New ${Num} Version",
      "version": 1
    },
    "translatedBy": "ai",
    "isTranslated": true,
    "version": 1
  },
  "Install_H_Model": {
    "value": "Quale modello AI vuoi utilizzare?",
    "original": {
      "value": "Which AI model would you like to use?",
      "version": 1
    },
    "translatedBy": "ai",
    "isTranslated": true,
    "version": 1
  },
  "Install_N_SkipLearn": {
    "value": "Salta e Inizia a Lavorare",
    "original": {
      "value": "Skip and Start Working"
    },
    "translatedBy": "ai",
    "isTranslated": true
  },
  "Settings_N_NAME-Loading": {
    "value": "Carica automaticamente l'ultima chat",
    "original": {
      "value": "Auto-load Last Chat"
    },
    "translatedBy": "ai",
    "isTranslated": true
  },
  "Settings_T_ID-Upd-False": {
    "value": "Disattivato",
    "original": {
      "value": "Turned Off",
      "version": 1
    },
    "translatedBy": "ai",
    "isTranslated": true,
    "version": 1
  },
  "Generation_N_Skip": {
    "value": "No, salta questa azione",
    "original": {
      "value": "No, Skip This Action",
      "version": 1
    },
    "translatedBy": "ai",
    "isTranslated": true,
    "version": 1
  },
  "Generation_H_Note": {
    "value": "Vuoi creare e salvare una nota “${Title}” con Nuvole AI?",
    "original": {
      "value": "Do you want to create and save a note “${Title}” with Nuvole AI?",
      "version": 1
    },
    "translatedBy": "ai",
    "isTranslated": true,
    "version": 1
  },
  "Settings_H_NAME-History": {
    "value": "Seleziona se vuoi visualizzare la cronologia della sessione",
    "original": {
      "value": "Select whether you want to display the session history",
      "version": 1
    },
    "translatedBy": "ai",
    "isTranslated": true,
    "version": 1
  },
  "Settings_H_NAME-Lang": {
    "value": "Scegli una lingua in cui ti sarà comodo lavorare con Nuvole AI",
    "original": {
      "value": "Choose a language in which it will be convenient for you to work with Nuvole AI",
      "version": 1
    },
    "translatedBy": "ai",
    "isTranslated": true,
    "version": 1
  },
  "Settings_T_C-Request": {
    "value": "Elaborazione della richiesta",
    "original": {
      "value": "Processing of the Request",
      "version": 1
    },
    "translatedBy": "ai",
    "isTranslated": true,
    "version": 1
  },
  "Settings_T_Font": {
    "value": "Il tuo valore: ${Num}",
    "original": {
      "value": "Your value: ${Num}",
      "version": 1
    },
    "translatedBy": "ai",
    "isTranslated": true,
    "version": 1
  },
  "Settings_N_Loading-True": {
    "value": "Riprendi Automaticamente l'Ultima Chat",
    "original": {
      "value": "Auto-Resume Last Chat"
    },
    "translatedBy": "ai",
    "isTranslated": true
  },
  "Settings_N_NAME-History": {
    "value": "Visualizzazione cronologia chat",
    "original": {
      "value": "Chat History Displaying",
      "version": 1
    },
    "translatedBy": "ai",
    "isTranslated": true,
    "version": 1
  },
  "Install_H_Main": {
    "value": "Vuoi aprire il menu principale quando esegui Nuvole AI?",
    "original": {
      "value": "Do you want to open the Main Menu when running Nuvole AI?",
      "version": 1
    },
    "translatedBy": "ai",
    "isTranslated": true,
    "version": 1
  },
  "Settings_H_Success": {
    "value": "L'impostazione è stata cambiata",
    "original": {
      "value": "The setting has been changed",
      "version": 1
    },
    "translatedBy": "ai",
    "isTranslated": true,
    "version": 1
  },
  "History_N_SearchBack": {
    "value": "Chiudi ricerca",
    "original": {
      "value": "Close Search",
      "version": 1
    },
    "translatedBy": "ai",
    "isTranslated": true,
    "version": 1
  },
  "Feedback_H_Input": {
    "value": "Descrivi in dettaglio il problema che hai riscontrato, insieme a eventuali domande o idee che hai per migliorare Nuvole AI",
    "original": {
      "value": "Describe in detail the problem you have encountered, along with any questions or ideas you have for improving Nuvole AI",
      "version": 1
    },
    "translatedBy": "ai",
    "isTranslated": true,
    "version": 1
  },
  "Settings_T_Stop": {
    "value": "Non vuoi cambiare le impostazioni di questo parametro?",
    "original": {
      "value": "Don’t want to change the settings of this parameter?",
      "version": 1
    },
    "translatedBy": "ai",
    "isTranslated": true,
    "version": 1
  },
  "Settings_T_ID-Summary-2": {
    "value": "Medio",
    "original": {
      "value": "Medium",
      "version": 1
    },
    "translatedBy": "ai",
    "isTranslated": true,
    "version": 1
  },
  "Settings_N_Search-True": {
    "value": "Cerca Automaticamente",
    "original": {
      "value": "Automatically Search"
    },
    "translatedBy": "ai",
    "isTranslated": true
  },
  "Update_T_21Changes": {
    "value": "21 modifiche",
    "original": {
      "value": "21 changes",
      "version": 1
    },
    "translatedBy": "ai",
    "isTranslated": true,
    "version": 1
  },
  "History_H_SearchDeletion": {
    "value": "Sei sicuro di voler eliminare ${Count} ${Chats} trovati? Puoi eliminare solo le chat necessarie selezionando “Seleziona ed Elimina Chat” nel menu precedente. Cliccando sul pulsante “Elimina Tutte le Chat Trovate”, accetti che tutte le chat trovate verranno eliminate senza possibilità di recupero.",
    "original": {
      "value": "Are you sure you want to delete ${Count} found ${Chats}? You can only delete the necessary chats by selecting “Select and Delete Chats” in the previous menu. By clicking on the “Delete All Found Chats” button, you agree that all found chats will be deleted without the possibility of recovery."
    },
    "translatedBy": "ai",
    "isTranslated": true
  },
  "Share_H_Pages": {
    "value": "Seleziona le pagine che vuoi utilizzare",
    "original": {
      "value": "Select the pages you want to use",
      "version": 1
    },
    "translatedBy": "ai",
    "isTranslated": true,
    "version": 1
  },
  "Error_H_Status": {
    "value": "Stato del server di ${Name}",
    "original": {
      "value": "Server status of ${Name}",
      "version": 1
    },
    "translatedBy": "ai",
    "isTranslated": true,
    "version": 1
  },
  "Error_H_Rate": {
    "value": "Tasso di errore per l'ultima ora",
    "original": {
      "value": "Error rate for last hour"
    },
    "translatedBy": "ai",
    "isTranslated": true
  },
  "Install_ORG_YesUpdates": {
    "value": "Consigliato per una migliore esperienza",
    "original": {
      "value": "Recommended for a better experience"
    },
    "translatedBy": "ai",
    "isTranslated": true
  },
  "Text_T_Hide": {
    "value": "Nascondi messaggio completo",
    "original": {
      "value": "Hide Full Message",
      "version": 1
    },
    "translatedBy": "ai",
    "isTranslated": true,
    "version": 1
  },
  "Settings_H_NAME-ImagePlus": {
    "value": "Seleziona se vuoi migliorare il prompt per generare immagini con l'AI",
    "original": {
      "value": "Select whether you want to improve prompt to generate images with AI",
      "version": 1
    },
    "translatedBy": "ai",
    "isTranslated": true,
    "version": 1
  },
  "Share_N_Question": {
    "value": "Fai la tua domanda",
    "original": {
      "value": "Ask Your Question",
      "version": 1
    },
    "translatedBy": "ai",
    "isTranslated": true,
    "version": 1
  },
  "Chat_ORG_Rename": {
    "value": "Cambia il nome della chat “${Text}” in un altro",
    "original": {
      "value": "Change the chat name “${Text}” to any other",
      "version": 1
    },
    "translatedBy": "ai",
    "isTranslated": true,
    "version": 1
  },
  "History_N_SearchChange": {
    "value": "Cambia query di ricerca",
    "original": {
      "value": "Change Search Query",
      "version": 1
    },
    "translatedBy": "ai",
    "isTranslated": true,
    "version": 1
  },
  "Feedback_T_End": {
    "value": "Grazie per il tuo feedback! Questo aiuterà a migliorare Nuvole AI!",
    "original": {
      "value": "Thank you for your feedback! This will help improve the Nuvole AI!",
      "version": 1
    },
    "translatedBy": "ai",
    "isTranslated": true,
    "version": 1
  },
  "Error_H_Error": {
    "value": "Errore",
    "original": {
      "value": "Error",
      "version": 1
    },
    "translatedBy": "ai",
    "isTranslated": true,
    "version": 1
  },
  "Share_N_Summary": {
    "value": "Fai un riassunto",
    "original": {
      "value": "Make a Summarization",
      "version": 1
    },
    "translatedBy": "ai",
    "isTranslated": true,
    "version": 1
  },
  "Chat_H_Renaming": {
    "value": "Quale nome vuoi dare a questa chat?",
    "original": {
      "value": "What name do you want to give this chat?",
      "version": 1
    },
    "translatedBy": "ai",
    "isTranslated": true,
    "version": 1
  },
  "Text_T_History": {
    "value": "La cronologia della chat “${Name}” è stata caricata.",
    "original": {
      "value": "The history of “${Name}” chat is loaded.",
      "version": 1
    },
    "translatedBy": "ai",
    "isTranslated": true,
    "version": 1
  },
  "Feedback_ORG_YesConfig": {
    "value": "Questo potrebbe chiarire il tuo problema",
    "original": {
      "value": "This could clarify your issue"
    },
    "translatedBy": "ai",
    "isTranslated": true
  },
  "Share_H_Input": {
    "value": "Cosa vuoi chiedere?",
    "original": {
      "value": "What do you want to ask?",
      "version": 1
    },
    "translatedBy": "ai",
    "isTranslated": true,
    "version": 1
  },
  "Install_H_Learn": {
    "value": "Il processo di installazione è completo! Vuoi saperne di più su Nuvole AI e le sue funzionalità?",
    "original": {
      "value": "The installation process is complete! Do you want to learn more about Nuvole AI and its features?"
    },
    "translatedBy": "ai",
    "isTranslated": true
  },
  "Settings_T_ID-Share-1": {
    "value": "Riassunto",
    "original": {
      "value": "Summarization",
      "version": 1
    },
    "translatedBy": "ai",
    "isTranslated": true,
    "version": 1
  },
  "Main_ORG_NewChat": {
    "value": "Inizia da zero",
    "original": {
      "value": "Start from scratch",
      "version": 1
    },
    "translatedBy": "ai",
    "isTranslated": true,
    "version": 1
  },
  "Settings_H_Settings": {
    "value": "Impostazioni",
    "original": {
      "value": "Settings",
      "version": 1
    },
    "translatedBy": "ai",
    "isTranslated": true,
    "version": 1
  },
  "Settings_T_C-More": {
    "value": "Aggiuntivo",
    "original": {
      "value": "Additional",
      "version": 1
    },
    "translatedBy": "ai",
    "isTranslated": true,
    "version": 1
  },
  "Update_T_Hidden": {
    "value": "Puoi installare questo aggiornamento in seguito tramite RoutineHub",
    "original": {
      "value": "You can later install this update via the RoutineHub",
      "version": 1
    },
    "translatedBy": "ai",
    "isTranslated": true,
    "version": 1
  },
  "Error_ORG_ChangeStop": {
    "value": "Ripeti la richiesta utilizzando ${Name}",
    "original": {
      "value": "Repeat request using ${Name}",
      "version": 1
    },
    "translatedBy": "ai",
    "isTranslated": true,
    "version": 1
  },
  "Error_T_Type-Error-2": {
    "value": "Si è verificato un errore durante il processo di pensiero!",
    "original": {
      "value": "An error occurred during the thinking process!"
    },
    "translatedBy": "ai",
    "isTranslated": true
  },
  "Chat_ORG_Icon": {
    "value": "Cambia l'icona della chat “${Text}” in un'altra",
    "original": {
      "value": "Change the chat icon “${Text}” to any other",
      "version": 1
    },
    "translatedBy": "ai",
    "isTranslated": true,
    "version": 1
  },
  "Settings_H_Error": {
    "value": "L'impostazione non è stata cambiata",
    "original": {
      "value": "The setting has not been changed",
      "version": 1
    },
    "translatedBy": "ai",
    "isTranslated": true,
    "version": 1
  },
  "Error_ORG_RestartLoad": {
    "value": "Questa chat verrà caricata automaticamente",
    "original": {
      "value": "This chat will load automatically",
      "version": 1
    },
    "translatedBy": "ai",
    "isTranslated": true,
    "version": 1
  },
  "History_H_Search": {
    "value": "Scrivi il testo con cui vuoi trovare le chat. Verranno controllati i nomi delle chat e il loro contenuto (non sensibile alle maiuscole, supporta regex).",
    "original": {
      "value": "Write the text by which you want to find chats. The names of the chats and their content will be checked (case insensitive, supports regex).",
      "version": 1
    },
    "translatedBy": "ai",
    "isTranslated": true,
    "version": 1
  },
  "Feedback_N_Server": {
    "value": "Anonimamente",
    "original": {
      "value": "Anonymously",
      "version": 1
    },
    "translatedBy": "ai",
    "isTranslated": true,
    "version": 1
  },
  "Error_ORG_Change": {
    "value": "Si applica a tutte le sessioni",
    "original": {
      "value": "Applies to all sessions"
    },
    "translatedBy": "ai",
    "isTranslated": true
  },
  "Text_T_New": {
    "value": "Ciao! Come posso aiutarti?",
    "original": {
      "value": "Hello! How can I help you?",
      "version": 1
    },
    "translatedBy": "ai",
    "isTranslated": true,
    "version": 1
  },
  "Settings_T_ID-Summary-3": {
    "value": "Grande",
    "original": {
      "value": "Big",
      "version": 1
    },
    "translatedBy": "ai",
    "isTranslated": true,
    "version": 1
  },
  "Settings_H_NAME-Summary": {
    "value": "Seleziona la dimensione del riassunto che vuoi ricevere",
    "original": {
      "value": "Select the size of summarization you want to receive",
      "version": 1
    },
    "translatedBy": "ai",
    "isTranslated": true,
    "version": 1
  },
  "History_ORG_BackMain": {
    "value": "Torna al menu principale",
    "original": {
      "value": "Return to Main Menu",
      "version": 1
    },
    "translatedBy": "ai",
    "isTranslated": true,
    "version": 1
  },
  "Share_ORG_Slides": {
    "value": "La tua presentazione sarà mostrata per prima",
    "original": {
      "value": "Your presentation will be shown first"
    },
    "translatedBy": "ai",
    "isTranslated": true
  },
  "Main_N_History": {
    "value": "Cronologia",
    "original": {
      "value": "History",
      "version": 1
    },
    "translatedBy": "ai",
    "isTranslated": true,
    "version": 1
  },
  "Settings_N_NAME-Summary": {
    "value": "Dimensione del riassunto",
    "original": {
      "value": "Summarization Size",
      "version": 1
    },
    "translatedBy": "ai",
    "isTranslated": true,
    "version": 1
  },
  "Settings_T_C-Html": {
    "value": "Visualizzazione della risposta",
    "original": {
      "value": "Displaying the Answer",
      "version": 1
    },
    "translatedBy": "ai",
    "isTranslated": true,
    "version": 1
  },
  "Settings_N_History-False": {
    "value": "Non Mostrare Cronologia",
    "original": {
      "value": "Do Not Display History"
    },
    "translatedBy": "ai",
    "isTranslated": true
  },
  "Main_N_Continue": {
    "value": "Riprendi questa chat",
    "original": {
      "value": "Resume This Chat"
    },
    "translatedBy": "ai",
    "isTranslated": true
  },
  "Settings_N_NAME-Voice": {
    "value": "Inserimento di una richiesta",
    "original": {
      "value": "Entering a Request",
      "version": 1
    },
    "translatedBy": "ai",
    "isTranslated": true,
    "version": 1
  },
  "Settings_H_NAME-Font": {
    "value": "Seleziona la dimensione del font per visualizzare la risposta (48 pixel di default)",
    "original": {
      "value": "Select the font size to display the response (48 pixels by default)",
      "version": 1
    },
    "translatedBy": "ai",
    "isTranslated": true,
    "version": 1
  },
  "Settings_N_NAME-Lang": {
    "value": "Lingua",
    "original": {
      "value": "Language"
    },
    "translatedBy": "ai",
    "isTranslated": true
  },
  "Settings_N_Lite": {
    "value": "Prova Nuvole AI Lite",
    "original": {
      "value": "Try Nuvole AI Lite"
    },
    "translatedBy": "ai",
    "isTranslated": true
  },
  "Settings_N_ImagePlus-True": {
    "value": "Migliorare Prompt",
    "original": {
      "value": "Improve Prompt"
    },
    "translatedBy": "ai",
    "isTranslated": true
  },
  "Error_T_Changing": {
    "value": "Non vuoi cambiare il modello?",
    "original": {
      "value": "Don’t want to change the model?",
      "version": 1
    },
    "translatedBy": "ai",
    "isTranslated": true,
    "version": 1
  },
  "Settings_N_NAME-Saving": {
    "value": "Salvataggio chat",
    "original": {
      "value": "Chat Saving",
      "version": 1
    },
    "translatedBy": "ai",
    "isTranslated": true,
    "version": 1
  },
  "Install_H_Input": {
    "value": "Seleziona il modo più comodo per te per inserire una richiesta per l'AI",
    "original": {
      "value": "Select the most convenient way for you to enter a request for AI",
      "version": 1
    },
    "translatedBy": "ai",
    "isTranslated": true,
    "version": 1
  },
  "History_ORG_SelectionDelete": {
    "value": "Elimina permanentemente queste chat",
    "original": {
      "value": "Permanently delete this chats"
    },
    "translatedBy": "ai",
    "isTranslated": true
  },
  "Install_T_Model": {
    "value": "Consigliato",
    "original": {
      "value": "Recomended",
      "version": 1
    },
    "translatedBy": "ai",
    "isTranslated": true,
    "version": 1
  },
  "Settings_T_ID-Voice-True": {
    "value": "Con voce",
    "original": {
      "value": "With Voice",
      "version": 1
    },
    "translatedBy": "ai",
    "isTranslated": true,
    "version": 1
  },
  "Settings_T_ID-Main-False": {
    "value": "Non aprire all'avvio",
    "original": {
      "value": "Don’t Open When Running",
      "version": 1
    },
    "translatedBy": "ai",
    "isTranslated": true,
    "version": 1
  },
  "Error_T_Type-Error-6": {
    "value": "Si è verificato un errore durante la generazione della nota!",
    "original": {
      "value": "An error occurred during note generation!"
    },
    "translatedBy": "ai",
    "isTranslated": true
  },
  "Share_N_AllPre": {
    "value": "Usa l'intera presentazione",
    "original": {
      "value": "Use the Whole Presentation",
      "version": 1
    },
    "translatedBy": "ai",
    "isTranslated": true,
    "version": 1
  },
  "Error_N_Repeat": {
    "value": "Ripeti la richiesta",
    "original": {
      "value": "Repeat Request",
      "version": 1
    },
    "translatedBy": "ai",
    "isTranslated": true,
    "version": 1
  },
  "Update_T_2Updates": {
    "value": "2 aggiornamenti",
    "original": {
      "value": "2 updates",
      "version": 1
    },
    "translatedBy": "ai",
    "isTranslated": true,
    "version": 1
  },
  "Notification_Response": {
    "value": "La risposta alla tua richiesta è pronta!",
    "original": {
      "value": "The response to your request is ready!"
    },
    "translatedBy": "ai",
    "isTranslated": true
  },
  "Settings_T_ID-Main-True": {
    "value": "Apri all'avvio",
    "original": {
      "value": "Open When Running",
      "version": 1
    },
    "translatedBy": "ai",
    "isTranslated": true,
    "version": 1
  },
  "Update_H_Hidden": {
    "value": "L'aggiornamento ${Num} è nascosto",
    "original": {
      "value": "Update ${Num} is hidden",
      "version": 1
    },
    "translatedBy": "ai",
    "isTranslated": true,
    "version": 1
  },
  "Feedback_N_Email": {
    "value": "Utilizzando l'email",
    "original": {
      "value": "Using Email",
      "version": 1
    },
    "translatedBy": "ai",
    "isTranslated": true,
    "version": 1
  },
  "ORG_Exit": {
    "value": "Arrivederci!",
    "original": {
      "value": "Goodbye!",
      "version": 1
    },
    "translatedBy": "ai",
    "isTranslated": true,
    "version": 1
  },
  "Settings_T_C-General": {
    "value": "Impostazioni generali",
    "original": {
      "value": "General Settings",
      "version": 1
    },
    "translatedBy": "ai",
    "isTranslated": true,
    "version": 1
  },
  "Update_T_2Changes": {
    "value": "2 modifiche",
    "original": {
      "value": "2 changes",
      "version": 1
    },
    "translatedBy": "ai",
    "isTranslated": true,
    "version": 1
  },
  "Update_T_21Updates": {
    "value": "21 aggiornamenti",
    "original": {
      "value": "21 updates",
      "version": 1
    },
    "translatedBy": "ai",
    "isTranslated": true,
    "version": 1
  },
  "Chat_H_Deletion": {
    "value": "Sei sicuro di voler eliminare la chat “${Text}”? Cliccando sul pulsante “Elimina chat”, accetti che questa chat verrà eliminata senza possibilità di recupero.",
    "original": {
      "value": "Are you sure you want to delete “${Text}” chat? By clicking on the “Delete chat” button, you agree that this chat will be deleted without the possibility of recovery.",
      "version": 1
    },
    "translatedBy": "ai",
    "isTranslated": true,
    "version": 1
  },
  "Settings_H_NAME-Share": {
    "value": "Seleziona cosa vuoi fare con gli elementi del menu “Foglio di condivisione”",
    "original": {
      "value": "Select what you want to do with the items from the “Share Sheet” menu",
      "version": 1
    },
    "translatedBy": "ai",
    "isTranslated": true,
    "version": 1
  },
  "History_N_SearchDelete": {
    "value": "Elimina tutte le chat trovate",
    "original": {
      "value": "Delete All Found Chats",
      "version": 1
    },
    "translatedBy": "ai",
    "isTranslated": true,
    "version": 1
  },
  "Share_H_BigFile": {
    "value": "Usare l'intero file? O alcune pagine?",
    "original": {
      "value": "Use the whole file? Or certain pages?",
      "version": 1
    },
    "translatedBy": "ai",
    "isTranslated": true,
    "version": 1
  },
  "Main_ORG_Settings": {
    "value": "Modifica e personalizza Nuvole AI",
    "original": {
      "value": "Modify and customize Nuvole AI"
    },
    "translatedBy": "ai",
    "isTranslated": true
  },
  "Text_T_ShowNote": {
    "value": "Mostra nota completa",
    "original": {
      "value": "Show Full Note",
      "version": 1
    },
    "translatedBy": "ai",
    "isTranslated": true,
    "version": 1
  },
  "History_T_21Chats": {
    "value": "21 chat",
    "original": {
      "value": "21 chats",
      "version": 1
    },
    "translatedBy": "ai",
    "isTranslated": true,
    "version": 1
  },
  "History_H_SelectionConfirm": {
    "value": "Sei sicuro di voler eliminare ${Count} ${Chats} selezionati? Cliccando sul pulsante “Elimina Chats Selezionati”, accetti che le chat che hai scelto verranno eliminate senza possibilità di recupero.",
    "original": {
      "value": "Are you sure you want to delete ${Count} selected ${Chats}? By clicking on the “Delete Selected Chats” button, you agree that chats you have choosen will be deleted without the possibility of recovery."
    },
    "translatedBy": "ai",
    "isTranslated": true
  },
  "Settings_N_Close": {
    "value": "Chiudi impostazioni",
    "original": {
      "value": "Close Settings",
      "version": 1
    },
    "translatedBy": "ai",
    "isTranslated": true,
    "version": 1
  },
  "History_ORG_SearchDeletionDelete": {
    "value": "Elimina permanentemente tutte le chat trovate",
    "original": {
      "value": "Permanently delete all found chats"
    },
    "translatedBy": "ai",
    "isTranslated": true
  },
  "Share_N_AllFile": {
    "value": "Usa l'intero file",
    "original": {
      "value": "Use the Whole File",
      "version": 1
    },
    "translatedBy": "ai",
    "isTranslated": true,
    "version": 1
  },
  "Error_N_Change": {
    "value": "Cambia modello e riprova",
    "original": {
      "value": "Change Model and Retry"
    },
    "translatedBy": "ai",
    "isTranslated": true
  },
  "Share_N_Slides": {
    "value": "Seleziona le diapositive da utilizzare",
    "original": {
      "value": "Select Slides to Use"
    },
    "translatedBy": "ai",
    "isTranslated": true
  },
  "Settings_T_ID-Theme-0": {
    "value": "Chiaro",
    "original": {
      "value": "Light",
      "version": 1
    },
    "translatedBy": "ai",
    "isTranslated": true,
    "version": 1
  },
  "History_N_DeletionStop": {
    "value": "Non eliminare",
    "original": {
      "value": "Do Not Delete",
      "version": 1
    },
    "translatedBy": "ai",
    "isTranslated": true,
    "version": 1
  },
  "Main_ORG_5Messages": {
    "value": "5 messaggi",
    "original": {
      "value": "5 messages",
      "version": 1
    },
    "translatedBy": "ai",
    "isTranslated": true,
    "version": 1
  },
  "Text_T_Else": {
    "value": "Forse qualcos'altro?",
    "original": {
      "value": "Maybe something else?",
      "version": 1
    },
    "translatedBy": "ai",
    "isTranslated": true,
    "version": 1
  },
  "Update_N_Hide": {
    "value": "Non offrire questo aggiornamento",
    "original": {
      "value": "Do Not Offer This Update",
      "version": 1
    },
    "translatedBy": "ai",
    "isTranslated": true,
    "version": 1
  },
  "Chat_N_Rename": {
    "value": "Rinomina chat",
    "original": {
      "value": "Rename Chat",
      "version": 1
    },
    "translatedBy": "ai",
    "isTranslated": true,
    "version": 1
  },
  "N_Exit": {
    "value": "Esci da Nuvole AI",
    "original": {
      "value": "Exit the Nuvole AI",
      "version": 1
    },
    "translatedBy": "ai",
    "isTranslated": true,
    "version": 1
  },
  "History_H_Deletion": {
    "value": "Sei sicuro di voler eliminare la cronologia? Puoi eliminare solo le chat necessarie selezionando “Seleziona ed Elimina Chat” nel menu precedente. Cliccando sul pulsante “Elimina Tutte le Chat”, accetti che tutte le chat verranno eliminate senza possibilità di recupero.",
    "original": {
      "value": "Are you sure you want to delete the history? You can only delete the necessary chats by selecting “Select and Delete Chats” in the previous menu. By clicking on the “Delete All Chats” button, you agree that all chats will be deleted without the possibility of recovery."
    },
    "translatedBy": "ai",
    "isTranslated": true
  },
  "Settings_T_C-Image": {
    "value": "Generazione immagine",
    "original": {
      "value": "Image Generation",
      "version": 1
    },
    "translatedBy": "ai",
    "isTranslated": true,
    "version": 1
  },
  "Update_N_NotInstall": {
    "value": "Non installare l'aggiornamento",
    "original": {
      "value": "Do Not Install the Update",
      "version": 1
    },
    "translatedBy": "ai",
    "isTranslated": true,
    "version": 1
  },
  "Share_H_VideoType": {
    "value": "Cosa vuoi fare con questo video?",
    "original": {
      "value": "What do you want to do with this video?",
      "version": 1
    },
    "translatedBy": "ai",
    "isTranslated": true,
    "version": 1
  },
  "Error_ORG_Replace": {
    "value": "Solo sessione, resetta a ${Name}",
    "original": {
      "value": "Session only, resets to ${Name}"
    },
    "translatedBy": "ai",
    "isTranslated": true
  },
  "Error_T_Type-Error-1": {
    "value": "Si è verificato un errore durante l'elaborazione della richiesta!",
    "original": {
      "value": "An error occurred during processing the request!"
    },
    "translatedBy": "ai",
    "isTranslated": true
  },
  "Settings_N_Saving-False": {
    "value": "Salva Solo Quando Richiesto",
    "original": {
      "value": "Save Only When Asked"
    },
    "translatedBy": "ai",
    "isTranslated": true
  },
  "History_T_Found": {
    "value": "Trovate ${Count chat} per la richiesta “${Text}”",
    "original": {
      "value": "${Count chats} found on request “${Text}”",
      "version": 1
    },
    "translatedBy": "ai",
    "isTranslated": true,
    "version": 1
  },
  "Feedback_H_History": {
    "value": "Vuoi condividere questa chat contenente i tuoi messaggi e le risposte dell'AI con lo sviluppatore?",
    "original": {
      "value": "Do you want to share this chat containing your messages and AI responses with developer?",
      "version": 1
    },
    "translatedBy": "ai",
    "isTranslated": true,
    "version": 1
  },
  "Feedback_N_YesConfig": {
    "value": "Sì, Trasmettere la Mia Configurazione",
    "original": {
      "value": "Yes, Transmit My Config"
    },
    "translatedBy": "ai",
    "isTranslated": true
  },
  "Error_N_Report": {
    "value": "Errore troppo frequente?",
    "original": {
      "value": "Too Frequent Error?"
    },
    "translatedBy": "ai",
    "isTranslated": true
  },
  "Share_N_Pages": {
    "value": "Seleziona le pagine da utilizzare",
    "original": {
      "value": "Select Pages to Use"
    },
    "translatedBy": "ai",
    "isTranslated": true
  },
  "Settings_T_FontErrorMax": {
    "value": "Hai impostato un valore troppo alto",
    "original": {
      "value": "You have set the value too high",
      "version": 1
    },
    "translatedBy": "ai",
    "isTranslated": true,
    "version": 1
  },
  "Feedback_ORG_Server": {
    "value": "Non puoi ottenere feedback dagli sviluppatori",
    "original": {
      "value": "You can’t get developer feedback"
    },
    "translatedBy": "ai",
    "isTranslated": true
  },
  "Install_ORG_Learn": {
    "value": "Sarai reindirizzato a RoutineHub",
    "original": {
      "value": "You will be redirected to RoutineHub"
    },
    "translatedBy": "ai",
    "isTranslated": true
  },
  "History_N_SelectionDelete": {
    "value": "Elimina ${Count} ${Chats} selezionati",
    "original": {
      "value": "Delete ${Count} Selected ${Chats}",
      "version": 1
    },
    "translatedBy": "ai",
    "isTranslated": true,
    "version": 1
  },
  "Update_H_5Versions": {
    "value": "5 versioni",
    "original": {
      "value": "5 versions",
      "version": 1
    },
    "translatedBy": "ai",
    "isTranslated": true,
    "version": 1
  },
  "History_N_Back": {
    "value": "Chiudi cronologia",
    "original": {
      "value": "Close History",
      "version": 1
    },
    "translatedBy": "ai",
    "isTranslated": true,
    "version": 1
  },
  "Settings_H_NAME-Saving": {
    "value": "Come vuoi salvare le nuove chat?",
    "original": {
      "value": "How do you want to save new chats?",
      "version": 1
    },
    "translatedBy": "ai",
    "isTranslated": true,
    "version": 1
  },
  "Settings_N_NAME-Font": {
    "value": "Dimensione del font",
    "original": {
      "value": "Font Size",
      "version": 1
    },
    "translatedBy": "ai",
    "isTranslated": true,
    "version": 1
  },
  "Share_T_ErrorExtension": {
    "value": "Purtroppo, Nuvole AI non può lavorare con file .{Extension}",
    "original": {
      "value": "Unfortunately, Nuvole AI cannot work with files .{Extension}",
      "version": 1
    },
    "translatedBy": "ai",
    "isTranslated": true,
    "version": 1
  },
  "Settings_T_FontErrorMin": {
    "value": "Hai impostato un valore troppo basso",
    "original": {
      "value": "You have set the value too small",
      "version": 1
    },
    "translatedBy": "ai",
    "isTranslated": true,
    "version": 1
  },
  "Settings_T_ID-Search-True": {
    "value": "Automaticamente",
    "original": {
      "value": "Automatically",
      "version": 1
    },
    "translatedBy": "ai",
    "isTranslated": true,
    "version": 1
  },
  "Error_N_ChangeStop": {
    "value": "Riprova utilizzando lo stesso modello",
    "original": {
      "value": "Retry Using the Same Model"
    },
    "translatedBy": "ai",
    "isTranslated": true
  },
  "Error_T_Type-Error-5": {
    "value": "Si è verificato un errore durante l'elaborazione dell'immagine!",
    "original": {
      "value": "An error occurred during processing the image!"
    },
    "translatedBy": "ai",
    "isTranslated": true
  },
  "Share_H_SummarySize": {
    "value": "Seleziona la dimensione del riassunto che vuoi ottenere",
    "original": {
      "value": "Select the size of summarization you want to get",
      "version": 1
    },
    "translatedBy": "ai",
    "isTranslated": true,
    "version": 1
  },
  "Update_H_21Versions": {
    "value": "21 versioni",
    "original": {
      "value": "21 versions",
      "version": 1
    },
    "translatedBy": "ai",
    "isTranslated": true,
    "version": 1
  },
  "Install_H_Updates": {
    "value": "Seleziona se vuoi ricevere notifiche sugli aggiornamenti",
    "original": {
      "value": "Select whether you want to receive notifications about updates",
      "version": 1
    },
    "translatedBy": "ai",
    "isTranslated": true,
    "version": 1
  },
  "Generation_N_Note": {
    "value": "Sì, genera e salva",
    "original": {
      "value": "Yes, Generate and Save"
    },
    "translatedBy": "ai",
    "isTranslated": true
  },
  "Feedback_N_NoConfig": {
    "value": "No, non trasmettere la configurazione",
    "original": {
      "value": "No, Not Transmit Config",
      "version": 1
    },
    "translatedBy": "ai",
    "isTranslated": true,
    "version": 1
  },
  "Chat_N_View": {
    "value": "Visualizza chat",
    "original": {
      "value": "View Chat",
      "version": 1
    },
    "translatedBy": "ai",
    "isTranslated": true,
    "version": 1
  },
  "Chat_N_DeletionDelete": {
    "value": "Elimina questa chat",
    "original": {
      "value": "Delete This Chat",
      "version": 1
    },
    "translatedBy": "ai",
    "isTranslated": true,
    "version": 1
  },
  "Chat_T_RenamingError": {
    "value": "Il nome della chat non può essere una stringa vuota",
    "original": {
      "value": "The chat name cannot be an empty string",
      "version": 1
    },
    "translatedBy": "ai",
    "isTranslated": true,
    "version": 1
  },
  "Settings_N_History-True": {
    "value": "Mostra Cronologia",
    "original": {
      "value": "Display History"
    },
    "translatedBy": "ai",
    "isTranslated": true
  },
  "Share_ORG_Pages": {
    "value": "Il tuo file sarà mostrato per primo",
    "original": {
      "value": "Your file will be shown first"
    },
    "translatedBy": "ai",
    "isTranslated": true
  },
  "History_T_5Chats": {
    "value": "5 chat",
    "original": {
      "value": "5 chats",
      "version": 1
    },
    "translatedBy": "ai",
    "isTranslated": true,
    "version": 1
  },
  "Settings_N_NAME-Share": {
    "value": "Tipo di richiesta",
    "original": {
      "value": "Request Type",
      "version": 1
    },
    "translatedBy": "ai",
    "isTranslated": true,
    "version": 1
  },
  "N_Back": {
    "value": "Indietro",
    "original": {
      "value": "Back",
      "version": 1
    },
    "translatedBy": "ai",
    "isTranslated": true,
    "version": 1
  },
  "Share_T_ErrorPre": {
    "value": "Purtroppo, Nuvole AI non può lavorare con questa presentazione",
    "original": {
      "value": "Unfortunately, Nuvole AI cannot work with this presentation",
      "version": 1
    },
    "translatedBy": "ai",
    "isTranslated": true,
    "version": 1
  },
  "Settings_N_Search-False": {
    "value": "Non Cercare",
    "original": {
      "value": "Do Not Search"
    },
    "translatedBy": "ai",
    "isTranslated": true
  },
  "History_ORG_Search": {
    "value": "Cerca tra le tue chat",
    "original": {
      "value": "Search among your chats",
      "version": 1
    },
    "translatedBy": "ai",
    "isTranslated": true,
    "version": 1
  },
  "Text_T_ShowThink": {
    "value": "Mostra pensieri completi",
    "original": {
      "value": "Show Full Throghts",
      "version": 1
    },
    "translatedBy": "ai",
    "isTranslated": true,
    "version": 1
  },
  "History_T_SearchError": {
    "value": "Non è stato trovato nulla per la tua richiesta",
    "original": {
      "value": "Nothing was found for your request",
      "version": 1
    },
    "translatedBy": "ai",
    "isTranslated": true,
    "version": 1
  },
  "Text_T_Exit": {
    "value": "Nuvole AI completerà il suo lavoro",
    "original": {
      "value": "Nuvole AI will complete its work",
      "version": 1
    },
    "translatedBy": "ai",
    "isTranslated": true,
    "version": 1
  },
  "Error_T_Outage": {
    "value": "Problemi parziali.",
    "original": {
      "value": "Partial problems.",
      "version": 1
    },
    "translatedBy": "ai",
    "isTranslated": true,
    "version": 1
  },
  "Settings_ORG_Selected": {
    "value": "Impostazione selezionata",
    "original": {
      "value": "Selected setting",
      "version": 1
    },
    "translatedBy": "ai",
    "isTranslated": true,
    "version": 1
  }
}
